numericpy/__init__.py
numericpy-0.0.1.dist-info/licenses/LICENSE.md
numericpy-0.0.1.dist-info/METADATA
numericpy-0.0.1.dist-info/WHEEL
numericpy-0.0.1.dist-info/top_level.txt
numericpy-0.0.1.dist-info/RECORD
